cloudguard_interfaces/__init__.py
cloudguard_interfaces/config.py
cloudguard_interfaces/main.py
cloudguard_interfaces/providers/aws/config.py
cloudguard_interfaces/providers/aws/interface.py
cloudguard_interfaces/providers/azure/config.py
cloudguard_interfaces/providers/azure/interface.py
cloudguard_interfaces/providers/gcp/config.py
cloudguard_interfaces/providers/gcp/interface.py
cloudguard_interfaces/providers.py
cloudguard_interfaces/utils/json.py
cloudguard_interfaces-1.0.0.dist-info/LICENSE
cloudguard_interfaces-1.0.0.dist-info/METADATA
cloudguard_interfaces-1.0.0.dist-info/WHEEL
cloudguard_interfaces-1.0.0.dist-info/RECORD
